{"Org":"Peak District National Park Authority","Data":"1","UID":"202300489","Org type":"Combined Authority","Org Type 2":"","City/Town":"Bakewell","Postcode":"DE45 1AE","lat":"53.221525","long":"-1.672604","Country":"England","Region":"E12000004","Region Name":"East Midlands","County":"E10000007","County Name":"Derbyshire","Local Authority":"E07000035","Local Authority Name":"Derbyshire Dales","Travel to Work Area":"E30000190","Travel to Work Area Name":"Chesterfield","Real Name":"Peak District National Park Authority","Website":"https://www.peakdistrict.gov.uk/home","Political - 2019-23":"","Political - 2023 -":"","Notes":"","Slug":"202300489","Scheme Provider 1":"Cyclescheme","Scheme Provider 2":"0","Scheme Provider 3":"0","Scheme Provider 4":"0","Scheme Max":"3000","Scheme Max2":"0","Average Uptake Rank":"641","Average Uptake Score":"4.455445545","Average Uptake Data Weakness":"0","Org Rank Type":"Combined Authority","Assistance Rank":"333","Org Type Assistance Rank":"2","Org Type Assistance Rank 2":"","Assistance Score":"21.90955014","Final Rank":"489","Org Type Final Rank":"2","Org Type Final Rank2":"","Final Score":"15.24149799","Assistance Rating":"**","Final Rating":"**","Fail to respond":"","Cycle to work uptake data comment":"","C2W Scheme":"Like 95% of surveyed organisations, a cycle to work scheme is avalible for staff.","Schemes":"This organisation's scheme provider is","Schemes part 2":"Cyclescheme.","Max Value":"This organisation has a maximum cycle to work value of £3000.","Max Value Flavour":"","secure cycle parking":"This organisation did not state they have secure bike storage, unlike 36% of organisations. This may mean they have no bike storage at all, or that there's a higher risk of bike theft.","Bike Hubs":"","Changing/shower":"","drying room":"","":"This organisation doesn't provide training, route guidance, or helps with organised rides to build cycling confidence.","Learn to Ride":"","Cycle training":"","team guided bike rides":"","1 to 1 support for route planning":"","Bike loan/hire scheme":"• The oportunity to loan a bike for a short period to see how cycling can work for you.","Ebike Hire/Loan":"","pool bikes for work related business":"If you're going out on buisness, this organisation has pool bikes you can borrow.","Dr Bike / Maintinance Events":"","communal bike maintenance tools":"","Cycling Discounts":"","Bike user Allowance":"","Stated cycling milage scheme":"Like 69% of organisations surveyed, this organisation follows HMRC guidance, providing a milage rate for those who cycle as part of their work"}