{"Org":"Gloucestershire Health and Care Nhs Trust","Data":"1","UID":"202300462","Org type":"NHS","Org Type 2":"Community / Mental Health","City/Town":"Gloucester","Postcode":"GL3 4AW","lat":"51.844174","long":"-2.177447","Country":"England","Region":"E12000009","Region Name":"South West","County":"E10000013","County Name":"Gloucestershire","Local Authority":"E07000083","Local Authority Name":"Tewkesbury","Travel to Work Area":"E30000209","Travel to Work Area Name":"Gloucester","Real Name":"Gloucestershire Health & Care NHS Foundation Trust","Website":"https://www.ghc.nhs.uk/","Political - 2019-23":"","Political - 2023 -":"","Notes":"","Slug":"202300462","Scheme Provider 1":"Vivup","Scheme Provider 2":"0","Scheme Provider 3":"0","Scheme Provider 4":"0","Scheme Max":"2500","Scheme Max2":"0","Average Uptake Rank":"411","Average Uptake Score":"8.910891089","Average Uptake Data Weakness":"1","Org Rank Type":"NHS","Assistance Rank":"343","Org Type Assistance Rank":"92","Org Type Assistance Rank 2":"10","Assistance Score":"21.65733838","Final Rank":"462","Org Type Final Rank":"105","Org Type Final Rank2":"18","Final Score":"16.05012619","Assistance Rating":"**","Final Rating":"**","Fail to respond":"","Cycle to work uptake data comment":"This organisation failed to provide data on the percentage of their staff that used a Cycle to Work Scheme","C2W Scheme":"Like 95% of surveyed organisations, a cycle to work scheme is avalible for staff.","Schemes":"This organisation's scheme provider is","Schemes part 2":"Vivup.","Max Value":"This organisation has a maximum cycle to work value of £2500.","Max Value Flavour":"While this limit shows they have recently reviewed the scheme, it suggests that the organisational group who did so does not have a broad understanding of bikes and ebikes on the market. This may affect who can reasonably ride to work, as they may not be able to afford the bike that will allow them to replace their car with a cargo bike, for example.","secure cycle parking":"This organisation is one of the 36% of organisations to offer secure bike parking.","Bike Hubs":"","Changing/shower":"This organisation offers showers and changing rooms, like a third of organisations surveyed.","drying room":"","":"This organisation doesn't provide training, route guidance, or helps with organised rides to build cycling confidence.","Learn to Ride":"","Cycle training":"","team guided bike rides":"","1 to 1 support for route planning":"","Bike loan/hire scheme":"","Ebike Hire/Loan":"","pool bikes for work related business":"","Dr Bike / Maintinance Events":"","communal bike maintenance tools":"","Cycling Discounts":"","Bike user Allowance":"","Stated cycling milage scheme":"Like 69% of organisations surveyed, this organisation follows HMRC guidance, providing a milage rate for those who cycle as part of their work"}