{"Org":"Somerset NHS Foundation Trust","Data":"1","UID":"202300568","Org type":"NHS","Org Type 2":"Combined","City/Town":"Yeovil","Postcode":"BA21 4AT","lat":"50.944843","long":"-2.634712","Country":"England","Region":"E12000009","Region Name":"South West","County":"","County Name":"","Local Authority":"E06000066","Local Authority Name":"Somerset","Travel to Work Area":"E30000293","Travel to Work Area Name":"Yeovil","Real Name":"Somerset NHS Foundation Trust","Website":"https://www.somersetft.nhs.uk/","Political - 2019-23":"","Political - 2023 -":"","Notes":"","Slug":"202300568","Scheme Provider 1":"Vivup","Scheme Provider 2":"0","Scheme Provider 3":"0","Scheme Provider 4":"0","Scheme Max":"5000","Scheme Max2":"0","Average Uptake Rank":"118","Average Uptake Score":"21.3490099","Average Uptake Data Weakness":"0","Org Rank Type":"NHS","Assistance Rank":"731","Org Type Assistance Rank":"181","Org Type Assistance Rank 2":"14","Assistance Score":"8.427869866","Final Rank":"568","Org Type Final Rank":"127","Org Type Final Rank2":"10","Final Score":"12.87639423","Assistance Rating":"*","Final Rating":"**","Fail to respond":"","Cycle to work uptake data comment":"","C2W Scheme":"Like 95% of surveyed organisations, a cycle to work scheme is avalible for staff.","Schemes":"This organisation's scheme provider is","Schemes part 2":"Vivup.","Max Value":"This organisation has a maximum cycle to work value of £5000.","Max Value Flavour":"","secure cycle parking":"This organisation did not state they have secure bike storage, unlike 36% of organisations. This may mean they have no bike storage at all, or that there's a higher risk of bike theft.","Bike Hubs":"","Changing/shower":"","drying room":"","":"This organisation doesn't provide training, route guidance, or helps with organised rides to build cycling confidence.","Learn to Ride":"","Cycle training":"","team guided bike rides":"","1 to 1 support for route planning":"","Bike loan/hire scheme":"","Ebike Hire/Loan":"","pool bikes for work related business":"","Dr Bike / Maintinance Events":"","communal bike maintenance tools":"","Cycling Discounts":"","Bike user Allowance":"","Stated cycling milage scheme":"Like 69% of organisations surveyed, this organisation follows HMRC guidance, providing a milage rate for those who cycle as part of their work"}