{"Org":"Derby City Council","Data":"1","UID":"202300334","Org type":"Council","Org Type 2":"Unitary Authority","City/Town":"Derby","Postcode":"DE1 2FS","lat":"52.923192","long":"-1.473997","Country":"England","Region":"E12000004","Region Name":"East Midlands","County":"","County Name":"","Local Authority":"E06000015","Local Authority Name":"Derby","Travel to Work Area":"E30000200","Travel to Work Area Name":"Derby","Real Name":"Derby City Council","Website":"http://www.derby.gov.uk/","Political - 2019-23":"Conservative","Political - 2023 -":"Labour","Notes":"","Slug":"202300334","Scheme Provider 1":"Halfords","Scheme Provider 2":"0","Scheme Provider 3":"0","Scheme Provider 4":"0","Scheme Max":"3000","Scheme Max2":"0","Average Uptake Rank":"376","Average Uptake Score":"9.430693069","Average Uptake Data Weakness":"0","Org Rank Type":"Council","Assistance Rank":"209","Org Type Assistance Rank":"64","Org Type Assistance Rank 2":"20","Assistance Score":"33.64617471","Final Rank":"334","Org Type Final Rank":"99","Org Type Final Rank2":"23","Final Score":"19.45921269","Assistance Rating":"**","Final Rating":"**","Fail to respond":"","Cycle to work uptake data comment":"","C2W Scheme":"Like 95% of surveyed organisations, a cycle to work scheme is avalible for staff.","Schemes":"This organisation's scheme provider is","Schemes part 2":"Halfords.","Max Value":"This organisation has a maximum cycle to work value of £3000.","Max Value Flavour":"","secure cycle parking":"This organisation is one of the 36% of organisations to offer secure bike parking.","Bike Hubs":"They state that they also have bike hubs, which has facilities that are specifically designed to enable cycling. Only 3% of organisations offer this.","Changing/shower":"","drying room":"","":"The following are provided to help you gain confidence in cycling:","Learn to Ride":"","Cycle training":"• Training to help you be more confident on the road","team guided bike rides":"","1 to 1 support for route planning":"","Bike loan/hire scheme":"","Ebike Hire/Loan":"• The oportunity to loan an ebike to see how that could fit into your life.","pool bikes for work related business":"","Dr Bike / Maintinance Events":"","communal bike maintenance tools":"","Cycling Discounts":"","Bike user Allowance":"","Stated cycling milage scheme":"Like 69% of organisations surveyed, this organisation follows HMRC guidance, providing a milage rate for those who cycle as part of their work"}