{"Org":"Imperial War Museum","Data":"0","UID":"202300898","Org type":"Museum","Org Type 2":"","City/Town":"London","Postcode":"SE1 6HZ","lat":"51.496008","long":"-0.108353","Country":"England","Region":"E12000007","Region Name":"London","County":"E13000001","County Name":"","Local Authority":"E09000028","Local Authority Name":"Southwark","Travel to Work Area":"E30000234","Travel to Work Area Name":"London","Real Name":"Imperial War Museum","Website":"https://www.iwm.org.uk/","Political - 2019-23":"","Political - 2023 -":"","Notes":"","Slug":"202300898","Scheme Provider 1":"","Scheme Provider 2":"","Scheme Provider 3":"","Scheme Provider 4":"","Scheme Max":"","Scheme Max2":"","Average Uptake Rank":"","Average Uptake Score":"","Average Uptake Data Weakness":"","Org Rank Type":"Recreation","Assistance Rank":"","Org Type Assistance Rank":"DNF","Org Type Assistance Rank 2":"DNF","Assistance Score":"","Final Rank":"","Org Type Final Rank":"DNF","Org Type Final Rank2":"DNF","Final Score":"","Assistance Rating":"No Response","Final Rating":"No Response","Fail to respond":"This organisation failed to respond within our allotted time to our data request under both the Freedom of Information Act and the Enviromental Information Regulations. This could mean that the email found was incorrect, the email failed, or that they are not responding at all.","Cycle to work uptake data comment":"","C2W Scheme":"","Schemes":"","Schemes part 2":"","Max Value":"","Max Value Flavour":"","secure cycle parking":"","Bike Hubs":"","Changing/shower":"","drying room":"","":"","Learn to Ride":"","Cycle training":"","team guided bike rides":"","1 to 1 support for route planning":"","Bike loan/hire scheme":"","Ebike Hire/Loan":"","pool bikes for work related business":"","Dr Bike / Maintinance Events":"","communal bike maintenance tools":"","Cycling Discounts":"","Bike user Allowance":"","Stated cycling milage scheme":""}